aviatrix_testlibs/__init__.py
aviatrix_testlibs/test_utils/ping.py
aviatrix_testlibs/test_utils/order_tests.cpython-311-x86_64-linux-gnu.so
aviatrix_testlibs/test_utils/__init__.py
aviatrix_testlibs/test_utils/backend_utils.cpython-311-x86_64-linux-gnu.so
aviatrix_testlibs/test_utils/test_utils.cpython-311-x86_64-linux-gnu.so
aviatrix_testlibs/test_ping/local_tests.py
aviatrix_testlibs/test_ping/remote_tests.py
aviatrix_testlibs/test_ping/__init__.py
aviatrix_testlibs/test_base/__init__.py
aviatrix_testlibs/test_base/base.cpython-311-x86_64-linux-gnu.so
aviatrix_testlibs/bin/find_test_subnet.cpython-311-x86_64-linux-gnu.so
aviatrix_testlibs/bin/__init__.py
aviatrix_testlibs/bin/deploy_test_ec2.cpython-311-x86_64-linux-gnu.so
aviatrix_testlibs/bin/core/AppExitStatus.cpython-311-x86_64-linux-gnu.so
aviatrix_testlibs/bin/core/logconf.cpython-311-x86_64-linux-gnu.so
aviatrix_testlibs/bin/core/ValueNotFoundException.cpython-311-x86_64-linux-gnu.so
aviatrix_testlibs/bin/core/ErrorStatusHandler.cpython-311-x86_64-linux-gnu.so
aviatrix_testlibs/bin/core/__init__.py
aviatrix_testlibs/bin/core/Globals.cpython-311-x86_64-linux-gnu.so
aviatrix_testlibs/bin/lib/aws.cpython-311-x86_64-linux-gnu.so
aviatrix_testlibs/bin/lib/s3.cpython-311-x86_64-linux-gnu.so
aviatrix_testlibs/bin/lib/avx_except.cpython-311-x86_64-linux-gnu.so
aviatrix_testlibs/bin/lib/commonlib_aws.cpython-311-x86_64-linux-gnu.so
aviatrix_testlibs/bin/lib/spoke.cpython-311-x86_64-linux-gnu.so
aviatrix_testlibs/bin/lib/commonlib.cpython-311-x86_64-linux-gnu.so
aviatrix_testlibs/bin/lib/nat.cpython-311-x86_64-linux-gnu.so
aviatrix_testlibs/bin/lib/__init__.py
aviatrix_testlibs/bin/lib/avx_https.cpython-311-x86_64-linux-gnu.so
aviatrix_testlibs/bin/lib/avx_cred.cpython-311-x86_64-linux-gnu.so
aviatrix_testlibs-0.11.5.dist-info/WHEEL
aviatrix_testlibs-0.11.5.dist-info/top_level.txt
aviatrix_testlibs-0.11.5.dist-info/entry_points.txt
aviatrix_testlibs-0.11.5.dist-info/RECORD
aviatrix_testlibs-0.11.5.dist-info/METADATA
