Metadata-Version: 2.4
Name: aviatrix-testlibs
Version: 0.11.5
Requires-Dist: bcrypt==4.3.0
Requires-Dist: boto3==1.24.22
Requires-Dist: botocore==1.27.22
Requires-Dist: cachetools==5.3.1
Requires-Dist: certifi==2020.12.5
Requires-Dist: cffi==1.17.1
Requires-Dist: chardet==4.0.0
Requires-Dist: cryptography==42.0.8
Requires-Dist: decorator==5.0.9
Requires-Dist: idna==2.10
Requires-Dist: Jinja2==3.0.3
Requires-Dist: jmespath==0.10.0
Requires-Dist: MarkupSafe==3.0.2
Requires-Dist: netaddr==0.9.0
Requires-Dist: packaging==21.3
Requires-Dist: parameterized==0.9.0
Requires-Dist: paramiko==3.3.1
Requires-Dist: py==1.10.0
Requires-Dist: pycparser==2.22
Requires-Dist: pydantic==1.9.0
Requires-Dist: PyNaCl==1.5.0
Requires-Dist: pyparsing==3.2.3
Requires-Dist: python-dateutil==2.8.1
Requires-Dist: PyYAML==6.0.2
Requires-Dist: requests==2.25.1
Requires-Dist: retry==0.9.2
Requires-Dist: s3transfer==0.6.0
Requires-Dist: six==1.16.0
Requires-Dist: typing_extensions==4.5.0
Requires-Dist: urllib3==1.26.4
Dynamic: requires-dist
